{"id":129384,"name":"ワカコ酒","name_cn":"和歌子酒","type":"动画","image":"74/4d/129384_vd3ir.jpg","link":"https://bgm.tv/subject/129384","eps":12,"collection":{"on_hold":55,"dropped":74,"wish":174,"collect":1405,"doing":66},"date":"2015-07-05","summary":"喜欢美味的酒和食物胜过其他任何东西的26岁OL，村崎和歌子。对于和歌子来说最治愈的事情，是在工作后独自一人走遍各处喝酒，毫不迟疑地穿过偶然见到的店的门帘，完全融入佳肴美酒的幸福瞬间。","rating":{"rank":3555,"total":923,"count":{"1":1,"2":0,"3":1,"4":7,"5":82,"6":253,"7":406,"8":152,"9":12,"10":9},"score":6.7},"updated_at":"2022-07-09T10:33:20+08:00"}